pipesubprocess/__init__.py
pipesubprocess/constants.py
pipesubprocess/exceptions.py
pipesubprocess/popen.py
pipesubprocess/popen_args.py
pipesubprocess/run.py
test/__init__.py
test/test.py
pipe_subprocess-0.3.6.dist-info/LICENSE
pipe_subprocess-0.3.6.dist-info/METADATA
pipe_subprocess-0.3.6.dist-info/WHEEL
pipe_subprocess-0.3.6.dist-info/top_level.txt
pipe_subprocess-0.3.6.dist-info/RECORD
