Metadata-Version: 2.1
Name: pipe-subprocess
Version: 0.3.6
Summary: Connects subprocesses as pipe easily
Home-page: https://github.com/ssk38/pipesubprocess
Author: Shusaku Miwa
Author-email: shusakumiwa@gmail.com
License: MIT
Platform: UNKNOWN
Classifier: Development Status :: 4 - Beta
Classifier: Environment :: Console
Classifier: Intended Audience :: Developers
Classifier: Programming Language :: Python
Classifier: License :: OSI Approved :: MIT License
